topsis_102003160/__init__.py
Topsis_Simran_102003160-0.1.dist-info/LICENSE.txt
Topsis_Simran_102003160-0.1.dist-info/METADATA
Topsis_Simran_102003160-0.1.dist-info/WHEEL
Topsis_Simran_102003160-0.1.dist-info/top_level.txt
Topsis_Simran_102003160-0.1.dist-info/RECORD
